Metadata-Version: 2.1
Name: Poly-REaDDIT
Version: 0.0.1
Summary: "Poly REaDDIT" A tool for gathering Reddit user information and also retrieve the related Polygon (MATIC) public address.
Home-page: https://github.com/aaarghhh/Poly-REaDDIT
Author: Aaarghhh
Author-email: giacomo@udontneed.it
License: MIT
License-File: LICENSE
